{
	"credit": "Made with Blockbench",
	"textures": {
		"0": "custom/omamorigrass",
		"particle": "custom/omamorigrass"
	},
	"elements": [
		{
			"name": "omamorigrass_0",
			"from": [10.5, 15.5, 8],
			"to": [14.5, 16, 8.5],
			"faces": {
				"north": {"uv": [10.5, 0.5, 14.5, 0], "rotation": 180, "texture": "#0"},
				"east": {"uv": [14, 0, 14.5, 0.5], "texture": "#0"},
				"south": {"uv": [10.5, 0, 14.5, 0.5], "texture": "#0"},
				"west": {"uv": [10.5, 0, 11, 0.5], "texture": "#0"},
				"up": {"uv": [14.5, 0, 10.5, 0.5], "rotation": 180, "texture": "#0"},
				"down": {"uv": [10.5, 0, 14.5, 0.5], "texture": "#0"}
			}
		},
		{
			"name": "omamorigrass_1",
			"from": [10, 15, 8],
			"to": [11, 15.5, 8.5],
			"faces": {
				"north": {"uv": [10, 1, 11, 0.5], "rotation": 180, "texture": "#0"},
				"east": {"uv": [10.5, 0.5, 11, 1], "texture": "#0"},
				"south": {"uv": [10, 0.5, 11, 1], "texture": "#0"},
				"west": {"uv": [10, 0.5, 10.5, 1], "texture": "#0"},
				"up": {"uv": [11, 0.5, 10, 1], "rotation": 180, "texture": "#0"},
				"down": {"uv": [10, 0.5, 11, 1], "texture": "#0"}
			}
		},
		{
			"name": "omamorigrass_2",
			"from": [14, 15, 8],
			"to": [15, 15.5, 8.5],
			"faces": {
				"north": {"uv": [14, 1, 15, 0.5], "rotation": 180, "texture": "#0"},
				"east": {"uv": [14.5, 0.5, 15, 1], "texture": "#0"},
				"south": {"uv": [14, 0.5, 15, 1], "texture": "#0"},
				"west": {"uv": [14, 0.5, 14.5, 1], "texture": "#0"},
				"up": {"uv": [15, 0.5, 14, 1], "rotation": 180, "texture": "#0"},
				"down": {"uv": [14, 0.5, 15, 1], "texture": "#0"}
			}
		},
		{
			"name": "omamorigrass_3",
			"from": [10, 1, 8],
			"to": [10.5, 15, 8.5],
			"faces": {
				"north": {"uv": [10, 15, 10.5, 1], "rotation": 180, "texture": "#0"},
				"east": {"uv": [10, 1, 10.5, 15], "texture": "#0"},
				"south": {"uv": [10, 1, 10.5, 15], "texture": "#0"},
				"west": {"uv": [10, 1, 10.5, 15], "texture": "#0"},
				"up": {"uv": [10.5, 1, 10, 1.5], "rotation": 180, "texture": "#0"},
				"down": {"uv": [10, 14.5, 10.5, 15], "texture": "#0"}
			}
		},
		{
			"name": "omamorigrass_4",
			"from": [14.5, 14, 8],
			"to": [15, 15, 8.5],
			"faces": {
				"north": {"uv": [14.5, 2, 15, 1], "rotation": 180, "texture": "#0"},
				"east": {"uv": [14.5, 1, 15, 2], "texture": "#0"},
				"south": {"uv": [14.5, 1, 15, 2], "texture": "#0"},
				"west": {"uv": [14.5, 1, 15, 2], "texture": "#0"},
				"up": {"uv": [15, 1, 14.5, 1.5], "rotation": 180, "texture": "#0"},
				"down": {"uv": [14.5, 1.5, 15, 2], "texture": "#0"}
			}
		},
		{
			"name": "omamorigrass_5",
			"from": [5.5, 1.5, 8],
			"to": [10, 14.5, 8.5],
			"faces": {
				"north": {"uv": [5.5, 14.5, 10, 1.5], "rotation": 180, "texture": "#0"},
				"east": {"uv": [9.5, 1.5, 10, 14.5], "texture": "#0"},
				"south": {"uv": [5.5, 1.5, 10, 14.5], "texture": "#0"},
				"west": {"uv": [5.5, 1.5, 6, 14.5], "texture": "#0"},
				"up": {"uv": [10, 1.5, 5.5, 2], "rotation": 180, "texture": "#0"},
				"down": {"uv": [5.5, 14, 10, 14.5], "texture": "#0"}
			}
		},
		{
			"name": "omamorigrass_6",
			"from": [10.5, 4, 8],
			"to": [12, 14.5, 8.5],
			"faces": {
				"north": {"uv": [10.5, 12, 12, 1.5], "rotation": 180, "texture": "#0"},
				"east": {"uv": [11.5, 1.5, 12, 12], "texture": "#0"},
				"south": {"uv": [10.5, 1.5, 12, 12], "texture": "#0"},
				"west": {"uv": [10.5, 1.5, 11, 12], "texture": "#0"},
				"up": {"uv": [12, 1.5, 10.5, 2], "rotation": 180, "texture": "#0"},
				"down": {"uv": [10.5, 11.5, 12, 12], "texture": "#0"}
			}
		},
		{
			"name": "omamorigrass_7",
			"from": [12, 14, 8],
			"to": [13.5, 14.5, 8.5],
			"faces": {
				"north": {"uv": [12, 2, 13.5, 1.5], "rotation": 180, "texture": "#0"},
				"east": {"uv": [13, 1.5, 13.5, 2], "texture": "#0"},
				"south": {"uv": [12, 1.5, 13.5, 2], "texture": "#0"},
				"west": {"uv": [12, 1.5, 12.5, 2], "texture": "#0"},
				"up": {"uv": [13.5, 1.5, 12, 2], "rotation": 180, "texture": "#0"},
				"down": {"uv": [12, 1.5, 13.5, 2], "texture": "#0"}
			}
		},
		{
			"name": "omamorigrass_8",
			"from": [5, 1.5, 8],
			"to": [5.5, 14, 8.5],
			"faces": {
				"north": {"uv": [5, 14.5, 5.5, 2], "rotation": 180, "texture": "#0"},
				"east": {"uv": [5, 2, 5.5, 14.5], "texture": "#0"},
				"south": {"uv": [5, 2, 5.5, 14.5], "texture": "#0"},
				"west": {"uv": [5, 2, 5.5, 14.5], "texture": "#0"},
				"up": {"uv": [5.5, 2, 5, 2.5], "rotation": 180, "texture": "#0"},
				"down": {"uv": [5, 14, 5.5, 14.5], "texture": "#0"}
			}
		},
		{
			"name": "omamorigrass_9",
			"from": [13.5, 13.5, 8],
			"to": [14.5, 14, 8.5],
			"faces": {
				"north": {"uv": [13.5, 2.5, 14.5, 2], "rotation": 180, "texture": "#0"},
				"east": {"uv": [14, 2, 14.5, 2.5], "texture": "#0"},
				"south": {"uv": [13.5, 2, 14.5, 2.5], "texture": "#0"},
				"west": {"uv": [13.5, 2, 14, 2.5], "texture": "#0"},
				"up": {"uv": [14.5, 2, 13.5, 2.5], "rotation": 180, "texture": "#0"},
				"down": {"uv": [13.5, 2, 14.5, 2.5], "texture": "#0"}
			}
		},
		{
			"name": "omamorigrass_10",
			"from": [4.5, 2, 8],
			"to": [5, 13.5, 8.5],
			"faces": {
				"north": {"uv": [4.5, 14, 5, 2.5], "rotation": 180, "texture": "#0"},
				"east": {"uv": [4.5, 2.5, 5, 14], "texture": "#0"},
				"south": {"uv": [4.5, 2.5, 5, 14], "texture": "#0"},
				"west": {"uv": [4.5, 2.5, 5, 14], "texture": "#0"},
				"up": {"uv": [5, 2.5, 4.5, 3], "rotation": 180, "texture": "#0"},
				"down": {"uv": [4.5, 13.5, 5, 14], "texture": "#0"}
			}
		},
		{
			"name": "omamorigrass_11",
			"from": [12, 5, 8],
			"to": [12.5, 13.5, 8.5],
			"faces": {
				"north": {"uv": [12, 11, 12.5, 2.5], "rotation": 180, "texture": "#0"},
				"east": {"uv": [12, 2.5, 12.5, 11], "texture": "#0"},
				"south": {"uv": [12, 2.5, 12.5, 11], "texture": "#0"},
				"west": {"uv": [12, 2.5, 12.5, 11], "texture": "#0"},
				"up": {"uv": [12.5, 2.5, 12, 3], "rotation": 180, "texture": "#0"},
				"down": {"uv": [12, 10.5, 12.5, 11], "texture": "#0"}
			}
		},
		{
			"name": "omamorigrass_12",
			"from": [12.5, 7, 8],
			"to": [13.5, 13, 8.5],
			"faces": {
				"north": {"uv": [12.5, 9, 13.5, 3], "rotation": 180, "texture": "#0"},
				"east": {"uv": [13, 3, 13.5, 9], "texture": "#0"},
				"south": {"uv": [12.5, 3, 13.5, 9], "texture": "#0"},
				"west": {"uv": [12.5, 3, 13, 9], "texture": "#0"},
				"up": {"uv": [13.5, 3, 12.5, 3.5], "rotation": 180, "texture": "#0"},
				"down": {"uv": [12.5, 8.5, 13.5, 9], "texture": "#0"}
			}
		},
		{
			"name": "omamorigrass_13",
			"from": [4, 2, 8],
			"to": [4.5, 12.5, 8.5],
			"faces": {
				"north": {"uv": [4, 14, 4.5, 3.5], "rotation": 180, "texture": "#0"},
				"east": {"uv": [4, 3.5, 4.5, 14], "texture": "#0"},
				"south": {"uv": [4, 3.5, 4.5, 14], "texture": "#0"},
				"west": {"uv": [4, 3.5, 4.5, 14], "texture": "#0"},
				"up": {"uv": [4.5, 3.5, 4, 4], "rotation": 180, "texture": "#0"},
				"down": {"uv": [4, 13.5, 4.5, 14], "texture": "#0"}
			}
		},
		{
			"name": "omamorigrass_14",
			"from": [13.5, 8.5, 8],
			"to": [14, 12.5, 8.5],
			"faces": {
				"north": {"uv": [13.5, 7.5, 14, 3.5], "rotation": 180, "texture": "#0"},
				"east": {"uv": [13.5, 3.5, 14, 7.5], "texture": "#0"},
				"south": {"uv": [13.5, 3.5, 14, 7.5], "texture": "#0"},
				"west": {"uv": [13.5, 3.5, 14, 7.5], "texture": "#0"},
				"up": {"uv": [14, 3.5, 13.5, 4], "rotation": 180, "texture": "#0"},
				"down": {"uv": [13.5, 7, 14, 7.5], "texture": "#0"}
			}
		},
		{
			"name": "omamorigrass_15",
			"from": [3.5, 2.5, 8],
			"to": [4, 11.5, 8.5],
			"faces": {
				"north": {"uv": [3.5, 13.5, 4, 4.5], "rotation": 180, "texture": "#0"},
				"east": {"uv": [3.5, 4.5, 4, 13.5], "texture": "#0"},
				"south": {"uv": [3.5, 4.5, 4, 13.5], "texture": "#0"},
				"west": {"uv": [3.5, 4.5, 4, 13.5], "texture": "#0"},
				"up": {"uv": [4, 4.5, 3.5, 5], "rotation": 180, "texture": "#0"},
				"down": {"uv": [3.5, 13, 4, 13.5], "texture": "#0"}
			}
		},
		{
			"name": "omamorigrass_16",
			"from": [14, 9.5, 8],
			"to": [14.5, 11.5, 8.5],
			"faces": {
				"north": {"uv": [14, 6.5, 14.5, 4.5], "rotation": 180, "texture": "#0"},
				"east": {"uv": [14, 4.5, 14.5, 6.5], "texture": "#0"},
				"south": {"uv": [14, 4.5, 14.5, 6.5], "texture": "#0"},
				"west": {"uv": [14, 4.5, 14.5, 6.5], "texture": "#0"},
				"up": {"uv": [14.5, 4.5, 14, 5], "rotation": 180, "texture": "#0"},
				"down": {"uv": [14, 6, 14.5, 6.5], "texture": "#0"}
			}
		},
		{
			"name": "omamorigrass_17",
			"from": [3, 2.5, 8],
			"to": [3.5, 10.5, 8.5],
			"faces": {
				"north": {"uv": [3, 13.5, 3.5, 5.5], "rotation": 180, "texture": "#0"},
				"east": {"uv": [3, 5.5, 3.5, 13.5], "texture": "#0"},
				"south": {"uv": [3, 5.5, 3.5, 13.5], "texture": "#0"},
				"west": {"uv": [3, 5.5, 3.5, 13.5], "texture": "#0"},
				"up": {"uv": [3.5, 5.5, 3, 6], "rotation": 180, "texture": "#0"},
				"down": {"uv": [3, 13, 3.5, 13.5], "texture": "#0"}
			}
		},
		{
			"name": "omamorigrass_18",
			"from": [2.5, 3, 8],
			"to": [3, 9.5, 8.5],
			"faces": {
				"north": {"uv": [2.5, 13, 3, 6.5], "rotation": 180, "texture": "#0"},
				"east": {"uv": [2.5, 6.5, 3, 13], "texture": "#0"},
				"south": {"uv": [2.5, 6.5, 3, 13], "texture": "#0"},
				"west": {"uv": [2.5, 6.5, 3, 13], "texture": "#0"},
				"up": {"uv": [3, 6.5, 2.5, 7], "rotation": 180, "texture": "#0"},
				"down": {"uv": [2.5, 12.5, 3, 13], "texture": "#0"}
			}
		},
		{
			"name": "omamorigrass_19",
			"from": [2, 3, 8],
			"to": [2.5, 8.5, 8.5],
			"faces": {
				"north": {"uv": [2, 13, 2.5, 7.5], "rotation": 180, "texture": "#0"},
				"east": {"uv": [2, 7.5, 2.5, 13], "texture": "#0"},
				"south": {"uv": [2, 7.5, 2.5, 13], "texture": "#0"},
				"west": {"uv": [2, 7.5, 2.5, 13], "texture": "#0"},
				"up": {"uv": [2.5, 7.5, 2, 8], "rotation": 180, "texture": "#0"},
				"down": {"uv": [2, 12.5, 2.5, 13], "texture": "#0"}
			}
		},
		{
			"name": "omamorigrass_20",
			"from": [1.5, 3.5, 8],
			"to": [2, 7.5, 8.5],
			"faces": {
				"north": {"uv": [1.5, 12.5, 2, 8.5], "rotation": 180, "texture": "#0"},
				"east": {"uv": [1.5, 8.5, 2, 12.5], "texture": "#0"},
				"south": {"uv": [1.5, 8.5, 2, 12.5], "texture": "#0"},
				"west": {"uv": [1.5, 8.5, 2, 12.5], "texture": "#0"},
				"up": {"uv": [2, 8.5, 1.5, 9], "rotation": 180, "texture": "#0"},
				"down": {"uv": [1.5, 12, 2, 12.5], "texture": "#0"}
			}
		},
		{
			"name": "omamorigrass_21",
			"from": [12.5, 6, 8],
			"to": [13, 7, 8.5],
			"faces": {
				"north": {"uv": [12.5, 10, 13, 9], "rotation": 180, "texture": "#0"},
				"east": {"uv": [12.5, 9, 13, 10], "texture": "#0"},
				"south": {"uv": [12.5, 9, 13, 10], "texture": "#0"},
				"west": {"uv": [12.5, 9, 13, 10], "texture": "#0"},
				"up": {"uv": [13, 9, 12.5, 9.5], "rotation": 180, "texture": "#0"},
				"down": {"uv": [12.5, 9.5, 13, 10], "texture": "#0"}
			}
		},
		{
			"name": "omamorigrass_22",
			"from": [1, 3.5, 8],
			"to": [1.5, 6.5, 8.5],
			"faces": {
				"north": {"uv": [1, 12.5, 1.5, 9.5], "rotation": 180, "texture": "#0"},
				"east": {"uv": [1, 9.5, 1.5, 12.5], "texture": "#0"},
				"south": {"uv": [1, 9.5, 1.5, 12.5], "texture": "#0"},
				"west": {"uv": [1, 9.5, 1.5, 12.5], "texture": "#0"},
				"up": {"uv": [1.5, 9.5, 1, 10], "rotation": 180, "texture": "#0"},
				"down": {"uv": [1, 12, 1.5, 12.5], "texture": "#0"}
			}
		},
		{
			"name": "omamorigrass_23",
			"from": [0.5, 4, 8],
			"to": [1, 5.5, 8.5],
			"faces": {
				"north": {"uv": [0.5, 12, 1, 10.5], "rotation": 180, "texture": "#0"},
				"east": {"uv": [0.5, 10.5, 1, 12], "texture": "#0"},
				"south": {"uv": [0.5, 10.5, 1, 12], "texture": "#0"},
				"west": {"uv": [0.5, 10.5, 1, 12], "texture": "#0"},
				"up": {"uv": [1, 10.5, 0.5, 11], "rotation": 180, "texture": "#0"},
				"down": {"uv": [0.5, 11.5, 1, 12], "texture": "#0"}
			}
		},
		{
			"name": "omamorigrass_24",
			"from": [10.5, 3, 8],
			"to": [11.5, 4, 8.5],
			"faces": {
				"north": {"uv": [10.5, 13, 11.5, 12], "rotation": 180, "texture": "#0"},
				"east": {"uv": [11, 12, 11.5, 13], "texture": "#0"},
				"south": {"uv": [10.5, 12, 11.5, 13], "texture": "#0"},
				"west": {"uv": [10.5, 12, 11, 13], "texture": "#0"},
				"up": {"uv": [11.5, 12, 10.5, 12.5], "rotation": 180, "texture": "#0"},
				"down": {"uv": [10.5, 12.5, 11.5, 13], "texture": "#0"}
			}
		},
		{
			"name": "omamorigrass_25",
			"from": [10.5, 2, 8],
			"to": [11, 3, 8.5],
			"faces": {
				"north": {"uv": [10.5, 14, 11, 13], "rotation": 180, "texture": "#0"},
				"east": {"uv": [10.5, 13, 11, 14], "texture": "#0"},
				"south": {"uv": [10.5, 13, 11, 14], "texture": "#0"},
				"west": {"uv": [10.5, 13, 11, 14], "texture": "#0"},
				"up": {"uv": [11, 13, 10.5, 13.5], "rotation": 180, "texture": "#0"},
				"down": {"uv": [10.5, 13.5, 11, 14], "texture": "#0"}
			}
		},
		{
			"name": "omamorigrass_26",
			"from": [6, 1, 8],
			"to": [10, 1.5, 8.5],
			"faces": {
				"north": {"uv": [6, 15, 10, 14.5], "rotation": 180, "texture": "#0"},
				"east": {"uv": [9.5, 14.5, 10, 15], "texture": "#0"},
				"south": {"uv": [6, 14.5, 10, 15], "texture": "#0"},
				"west": {"uv": [6, 14.5, 6.5, 15], "texture": "#0"},
				"up": {"uv": [10, 14.5, 6, 15], "rotation": 180, "texture": "#0"},
				"down": {"uv": [6, 14.5, 10, 15], "texture": "#0"}
			}
		},
		{
			"name": "omamorigrass_27",
			"from": [7, 0.5, 8],
			"to": [10, 1, 8.5],
			"faces": {
				"north": {"uv": [7, 15.5, 10, 15], "rotation": 180, "texture": "#0"},
				"east": {"uv": [9.5, 15, 10, 15.5], "texture": "#0"},
				"south": {"uv": [7, 15, 10, 15.5], "texture": "#0"},
				"west": {"uv": [7, 15, 7.5, 15.5], "texture": "#0"},
				"up": {"uv": [10, 15, 7, 15.5], "rotation": 180, "texture": "#0"},
				"down": {"uv": [7, 15, 10, 15.5], "texture": "#0"}
			}
		},
		{
			"name": "omamorigrass_28",
			"from": [8, 0, 8],
			"to": [9.5, 0.5, 8.5],
			"faces": {
				"north": {"uv": [8, 16, 9.5, 15.5], "rotation": 180, "texture": "#0"},
				"east": {"uv": [9, 15.5, 9.5, 16], "texture": "#0"},
				"south": {"uv": [8, 15.5, 9.5, 16], "texture": "#0"},
				"west": {"uv": [8, 15.5, 8.5, 16], "texture": "#0"},
				"up": {"uv": [9.5, 15.5, 8, 16], "rotation": 180, "texture": "#0"},
				"down": {"uv": [8, 15.5, 9.5, 16], "texture": "#0"}
			}
		}
	],
	"display": {
		"thirdperson_righthand": {
			"translation": [0, 2, 0],
			"scale": [0.5, 0.5, 0.5]
		},
		"thirdperson_lefthand": {
			"translation": [0, 2, 0],
			"scale": [0.5, 0.5, 0.5]
		},
		"firstperson_righthand": {
			"translation": [0, 2, 0],
			"scale": [0.5, 0.5, 0.5]
		},
		"firstperson_lefthand": {
			"translation": [0, 2, 0],
			"scale": [0.5, 0.5, 0.5]
		},
		"ground": {
			"scale": [0.5, 0.5, 0.5]
		},
		"fixed": {
			"rotation": [0, -180, 0]
		}
	},
	"groups": [
		{
			"name": "omamorigrass",
			"origin": [8, 8, 8],
			"children": [0, 1, 2, 3, 4, 5, 6, 7, 8, 9, 10, 11, 12, 13, 14, 15, 16, 17, 18, 19, 20, 21, 22, 23, 24, 25, 26, 27, 28]
		}
	]
}